twitter_makeup/__init__.py
twitter_makeup-1.0.1.dist-info/LICENSE
twitter_makeup-1.0.1.dist-info/METADATA
twitter_makeup-1.0.1.dist-info/WHEEL
twitter_makeup-1.0.1.dist-info/top_level.txt
twitter_makeup-1.0.1.dist-info/RECORD
