Metadata-Version: 2.1
Name: twitter-makeup
Version: 1.0.1
Summary: Make up your twitter profile, from 🐴 to 🦄 !
Home-page: https://github.com/nidup/twitter-makeup
Author: Nicolas Dupont
Author-email: duponn@gmail.com
License: MIT
Download-URL: https://pypi.org/project/twitter-makeup
Keywords: Twitter,Profile,API
Platform: UNKNOWN
Requires-Dist: tweepy (>=3.8.0)
